tidb_mcp_server/__init__.py
tidb_mcp_server/main.py
tidb_mcp_server-0.1.0.dist-info/licenses/LICENSE
tidb_mcp_server-0.1.0.dist-info/METADATA
tidb_mcp_server-0.1.0.dist-info/WHEEL
tidb_mcp_server-0.1.0.dist-info/entry_points.txt
tidb_mcp_server-0.1.0.dist-info/top_level.txt
tidb_mcp_server-0.1.0.dist-info/RECORD
