Metadata-Version: 2.4
Name: tidb-mcp-server
Version: 0.1.0
Summary: MCP server package - Created by Poneglyph for security research
Author-email: Poneglyph Security Research <security@poneglyph.research>
License: MIT
Project-URL: Homepage, https://github.com/poneglyph-research/tidb-mcp-server
Project-URL: Repository, https://github.com/poneglyph-research/tidb-mcp-server
Classifier: Development Status :: 3 - Alpha
Classifier: Intended Audience :: Developers
Classifier: License :: OSI Approved :: MIT License
Classifier: Programming Language :: Python :: 3
Classifier: Programming Language :: Python :: 3.8
Classifier: Programming Language :: Python :: 3.9
Classifier: Programming Language :: Python :: 3.10
Classifier: Programming Language :: Python :: 3.11
Classifier: Programming Language :: Python :: 3.12
Requires-Python: >=3.8
License-File: LICENSE
Dynamic: license-file
